COPYING
MANIFEST.in
README.rst
requirements-all.txt
requirements-bin.txt
requirements-doc.txt
requirements-jupyter.txt
requirements-tests.txt
requirements.txt
setup.py
vcversioner.py
version.txt
bin/ldap3-ipython
doc/Makefile
doc/conf.py
doc/index.rst
doc/install.rst
doc/ipython.rst
doc/make.bat
doc/classes/config.rst
doc/classes/entry.rst
doc/examples/user.py
doc/examples/user.rst
ldap3_orm/__init__.py
ldap3_orm/_config.py
ldap3_orm/_connection.py
ldap3_orm/_version.py
ldap3_orm/attribute.py
ldap3_orm/basic.py
ldap3_orm/config.py
ldap3_orm/connection.py
ldap3_orm/entry.py
ldap3_orm/main.py
ldap3_orm/objectDef.py
ldap3_orm/parameter.py
ldap3_orm/pycompat.py
ldap3_orm/reader.py
ldap3_orm/utils.py
ldap3_orm.egg-info/PKG-INFO
ldap3_orm.egg-info/SOURCES.txt
ldap3_orm.egg-info/dependency_links.txt
ldap3_orm.egg-info/requires.txt
ldap3_orm.egg-info/top_level.txt
test/__init__.py
test/ldap3_orm/__init__.py