Metadata-Version: 2.1
Name: ldap3-orm
Version: 2.7.0
Summary: ldap3-orm, object-relational mapping for ldap3
Home-page: https://github.com/cfelder/ldap3-orm
Author: Christian Felder
Author-email: webmaster@bsm-felder.de
License: LGPL-3.0+
Platform: UNKNOWN
Classifier: Development Status :: 5 - Production/Stable
Classifier: Intended Audience :: Developers
Classifier: Intended Audience :: System Administrators
Classifier: License :: OSI Approved :: GNU Lesser General Public License v3 or later (LGPLv3+)
Classifier: Natural Language :: English
Classifier: Operating System :: OS Independent
Classifier: Programming Language :: Python
Classifier: Programming Language :: Python :: 2
Classifier: Programming Language :: Python :: 3
Classifier: Topic :: Software Development
Classifier: Topic :: Software Development :: Libraries
Classifier: Topic :: System :: Systems Administration
Classifier: Topic :: System :: Systems Administration :: Authentication/Directory
Classifier: Topic :: System :: Systems Administration :: Authentication/Directory :: LDAP
Provides-Extra: all
Provides-Extra: ipython
Provides-Extra: jupyter
